compic10/__main__.py
compic10/codegen.py
compic10/compilerexception.py
compic10/compilerutil.py
compic10/postprocess.py
compic10/programdatabase.py
compic10/syntax.py
compic10/tokens.py
compic10/vm/__main__.py
compic10/vm/instructionset.py
compic10/vm/processor.py
compic10-1.1.2.dist-info/entry_points.txt
compic10-1.1.2.dist-info/LICENSE
compic10-1.1.2.dist-info/WHEEL
compic10-1.1.2.dist-info/METADATA
compic10-1.1.2.dist-info/RECORD
