Metadata-Version: 2.1
Name: compic10
Version: 1.1.2
Summary: A fully fledged compiler and emulator for the IC10-MIPS processor of the game Stationeers.
Home-page: https://gitlab.com/smpkdev/compic10
Author: Florian Ullmann
Author-email: florian.ullmann@protonmail.com
Requires-Python: >=3.7,<4.0
Classifier: License :: OSI Approved :: GNU Affero General Public License v3
Classifier: Operating System :: OS Independent
Classifier: Programming Language :: Python :: 3
Classifier: Programming Language :: Python :: 3.10
Classifier: Programming Language :: Python :: 3.7
Classifier: Programming Language :: Python :: 3.8
Classifier: Programming Language :: Python :: 3.9
Requires-Dist: PyYAML (>=6.0,<7.0)
Requires-Dist: clipboard (>=0.0.4,<0.0.5)
Project-URL: Bug Tracker, https://gitlab.com/smpkdev/compic10/-/issues
Project-URL: Repository, https://gitlab.com/smpkdev/compic10
